{
    "class": "TemplateMatchElement", 
    "elem_shot_file_path": null, 
    "hash": "u4Qd0AH5Gj76vZzBrKp8fg==\n", 
    "height": 38, 
    "hier_level": 0, 
    "human_hash": "TemplateMatchElement_X426_Y429_W213_H38", 
    "index": -1, 
    "label": "btn_wait_for_tmp", 
    "labels": [
        "btn_wait_for_tmp"
    ], 
    "score": 0.9980252385139465, 
    "tag_name": "TemplateMatchElement", 
    "template": "/Users/bot/test_ai/templates/btn_wait_for_tmp/btn_wait_for_tmp.png", 
    "text": "", 
    "width": 213, 
    "x": 426, 
    "y": 429
}