{
    "behavior": "", 
    "checkable": true, 
    "checked": true, 
    "class": "input", 
    "clickable": true, 
    "content-desc": "", 
    "elem_shot_file_path": "/Users/bot/test_ai/apps/60f11fb5-ea80-44d0-a9a5-6ae2bbdb1a33/builds/34aaaeb4-52c5-4fe3-b687-5a99e729419d/crawls/20210406190010/tmpZ/input_X827_Y558_W13_H13.png", 
    "enabled": true, 
    "focusable": true, 
    "focused": false, 
    "hash": "4shXbKHhjt3YN0J9r9Xz7Q==\n", 
    "height": 13, 
    "hier_level": 0, 
    "human_hash": "input_X827_Y558_W13_H13", 
    "human_readable": "input_827_558_13_13_input_fffffffffffffffffffffffffffef03cc01cc00c87848fc48fe48ffc1ffc1ffc_9d4568c009d203ab10e33ea9953a0264", 
    "img_hash": "87815c79cfcb50762e03529cc6779fcf", 
    "index": -1, 
    "internal": {
        "elem_dict": {
            "attributes": {
                "class": "custom-control-input", 
                "id": "customCheck1", 
                "type": "checkbox"
            }, 
            "background-color": "rgba(0, 0, 0, 0)", 
            "class": "input", 
            "color": "rgb(0, 0, 0)", 
            "cssClass": "custom-control-input", 
            "domLevel": 11, 
            "flags": {
                "checkable": true, 
                "checked": true, 
                "clickable": true, 
                "enabled": true, 
                "focusable": true, 
                "focused": false, 
                "scrollable": false
            }, 
            "font-family": "-apple-system, system-ui, \"Segoe UI\", Roboto, \"Helvetica Neue\", Arial, sans-serif, \"Apple Color Emoji\", \"Segoe UI Emoji\", \"Segoe UI Symbol\"", 
            "font-weight": "400", 
            "fontSize": 16, 
            "height": 13, 
            "identifier": "customCheck1", 
            "is-focused": false, 
            "is-hidden": false, 
            "name": "", 
            "tagName": "input", 
            "text": "", 
            "type": "checkbox", 
            "value": "on", 
            "width": 13, 
            "x": 827, 
            "xPercent": 43.063151041666664, 
            "y": 558, 
            "yPercent": 50.40650406504065
        }, 
        "location": {
            "x": 827, 
            "y": 558
        }, 
        "size": {
            "height": 13, 
            "width": 13
        }, 
        "tag_name": "input", 
        "text": ""
    }, 
    "is_transformed": true, 
    "package": "", 
    "password": false, 
    "resource-id": "", 
    "scrollable": false, 
    "tag_name": "input", 
    "text": "", 
    "text_hash": "9d4568c009d203ab10e33ea9953a0264", 
    "transformed": true, 
    "width": 13, 
    "x": 827, 
    "y": 558
}