{
    "behavior": "", 
    "checkable": false, 
    "class": "h3", 
    "clickable": false, 
    "content-desc": "", 
    "elem_shot_file_path": "/Users/bot/test_ai/apps/60f11fb5-ea80-44d0-a9a5-6ae2bbdb1a33/builds/34aaaeb4-52c5-4fe3-b687-5a99e729419d/crawls/20210326005538/tmpZ/h3_X1281_Y653_W213_H33.png", 
    "enabled": false, 
    "focusable": false, 
    "focused": false, 
    "hash": "c0OqorXglSyTcaGdMdrhYA==\n", 
    "height": 33, 
    "hier_level": 0, 
    "human_hash": "h3_X1281_Y653_W213_H33", 
    "human_readable": "h3_1281_653_213_33_h3_00000000000006000600060007e007e007e007e007e007e007e0020000000000_a6d756f02d69a011f1a76f5dbc8f3ac6", 
    "img_hash": "91c6e0c7e19f8d1f168e6c9895f088a4", 
    "index": -1, 
    "internal": {
        "elem_dict": {
            "attributes": {}, 
            "background-color": "rgba(0, 0, 0, 0)", 
            "class": "h3", 
            "color": "rgb(255, 255, 255)", 
            "domLevel": 8, 
            "flags": {
                "checkable": false, 
                "clickable": false, 
                "enabled": false, 
                "focusable": false, 
                "focused": false, 
                "scrollable": false
            }, 
            "font-family": "-apple-system, system-ui, \"Segoe UI\", Roboto, \"Helvetica Neue\", Arial, sans-serif, \"Apple Color Emoji\", \"Segoe UI Emoji\", \"Segoe UI Symbol\"", 
            "font-weight": "500", 
            "fontSize": 28, 
            "height": 33, 
            "identifier": "", 
            "is-focused": false, 
            "is-hidden": false, 
            "name": "", 
            "tagName": "h3", 
            "text": "Users", 
            "type": "", 
            "value": "", 
            "width": 213, 
            "x": 1281, 
            "xPercent": 66.71875, 
            "y": 653, 
            "yPercent": 63.583252190847126
        }, 
        "location": {
            "x": 1281, 
            "y": 653
        }, 
        "size": {
            "height": 33, 
            "width": 213
        }, 
        "tag_name": "h3", 
        "text": "Users"
    }, 
    "is_transformed": true, 
    "package": "", 
    "password": false, 
    "resource-id": "", 
    "scrollable": false, 
    "tag_name": "h3", 
    "text": "Users", 
    "text_hash": "a6d756f02d69a011f1a76f5dbc8f3ac6", 
    "transformed": true, 
    "width": 213, 
    "x": 1281, 
    "y": 653
}