{
    "behavior": "", 
    "checkable": false, 
    "class": "h3", 
    "clickable": false, 
    "content-desc": "", 
    "elem_shot_file_path": "/Users/bot/test_ai/apps/60f11fb5-ea80-44d0-a9a5-6ae2bbdb1a33/builds/34aaaeb4-52c5-4fe3-b687-5a99e729419d/crawls/20210326005538/tmpZ/h3_X1281_Y378_W213_H33.png", 
    "enabled": false, 
    "focusable": false, 
    "focused": false, 
    "hash": "KCkEWIfmywpJzpDl3AHEIA==\n", 
    "height": 33, 
    "hier_level": 0, 
    "human_hash": "h3_X1281_Y378_W213_H33", 
    "human_readable": "h3_1281_378_213_33_h3_000000000000102018201c001ff80ff817f80ff81ff81ff81ff8018001800180_885ac81c09459d8d9d5241f54127e04f", 
    "img_hash": "9a342e75ca3bf2a33e089206982ca1fc", 
    "index": -1, 
    "internal": {
        "elem_dict": {
            "attributes": {}, 
            "background-color": "rgba(0, 0, 0, 0)", 
            "class": "h3", 
            "color": "rgb(255, 255, 255)", 
            "domLevel": 8, 
            "flags": {
                "checkable": false, 
                "clickable": false, 
                "enabled": false, 
                "focusable": false, 
                "focused": false, 
                "scrollable": false
            }, 
            "font-family": "-apple-system, system-ui, \"Segoe UI\", Roboto, \"Helvetica Neue\", Arial, sans-serif, \"Apple Color Emoji\", \"Segoe UI Emoji\", \"Segoe UI Symbol\"", 
            "font-weight": "500", 
            "fontSize": 28, 
            "height": 33, 
            "identifier": "", 
            "is-focused": false, 
            "is-hidden": false, 
            "name": "", 
            "tagName": "h3", 
            "text": "Categories", 
            "type": "", 
            "value": "", 
            "width": 213, 
            "x": 1281, 
            "xPercent": 66.71875, 
            "y": 378, 
            "yPercent": 36.806231742940604
        }, 
        "location": {
            "x": 1281, 
            "y": 378
        }, 
        "size": {
            "height": 33, 
            "width": 213
        }, 
        "tag_name": "h3", 
        "text": "Categories"
    }, 
    "is_transformed": true, 
    "package": "", 
    "password": false, 
    "resource-id": "", 
    "scrollable": false, 
    "tag_name": "h3", 
    "text": "Categories", 
    "text_hash": "885ac81c09459d8d9d5241f54127e04f", 
    "transformed": true, 
    "width": 213, 
    "x": 1281, 
    "y": 378
}