{
    "behavior": "", 
    "checkable": false, 
    "class": "a", 
    "clickable": true, 
    "content-desc": "", 
    "enabled": false, 
    "focusable": true, 
    "focused": false, 
    "hash": "3bY2RohIdRuaeKu1AoaJRw==\n", 
    "height": 38, 
    "hier_level": 0, 
    "human_hash": "a_X405_Y121_W255_H38", 
    "internal": {
        "elem_dict": {
            "attributes": {
                "class": "btn btn-light btn-block", 
                "href": "index.html"
            }, 
            "background-color": "rgb(248, 249, 250)", 
            "class": "a", 
            "color": "rgb(33, 37, 41)", 
            "cssClass": "btn btn-light btn-block", 
            "domLevel": 6, 
            "flags": {
                "checkable": false, 
                "clickable": true, 
                "enabled": false, 
                "focusable": true, 
                "focused": false, 
                "scrollable": false
            }, 
            "font-family": "-apple-system, system-ui, \"Segoe UI\", Roboto, \"Helvetica Neue\", Arial, \"Noto Sans\", sans-serif, \"Apple Color Emoji\", \"Segoe UI Emoji\", \"Segoe UI Symbol\", \"Noto Color Emoji\"", 
            "font-weight": "400", 
            "fontSize": 16, 
            "height": 38, 
            "identifier": "", 
            "is-focused": false, 
            "is-hidden": false, 
            "name": "", 
            "tagName": "a", 
            "text": "Back to Dashboard", 
            "type": "", 
            "value": "", 
            "width": 255, 
            "x": 405, 
            "xPercent": 21.09375, 
            "y": 121, 
            "yPercent": 11.781888997078871
        }, 
        "location": {
            "x": 405, 
            "y": 121
        }, 
        "size": {
            "height": 38, 
            "width": 255
        }, 
        "tag_name": "a", 
        "text": "Back to Dashboard"
    }, 
    "is_transformed": true, 
    "package": "", 
    "password": false, 
    "resource-id": "", 
    "scrollable": false, 
    "tag_name": "a", 
    "text": "Back to Dashboard", 
    "transformed": true, 
    "width": 255, 
    "x": 405, 
    "y": 121
}