{
    "behavior": "", 
    "checkable": false, 
    "class": "a", 
    "clickable": true, 
    "content-desc": "", 
    "enabled": false, 
    "focusable": true, 
    "focused": false, 
    "hash": "31LApWuKlcVE+nMibpxrxw==\n", 
    "height": 38, 
    "hier_level": 0, 
    "human_hash": "a_X584_Y728_W36_H38", 
    "index": -1, 
    "internal": {
        "elem_dict": {
            "attributes": {
                "class": "page-link", 
                "href": "#"
            }, 
            "background-color": "rgb(255, 255, 255)", 
            "class": "a", 
            "color": "rgb(0, 123, 255)", 
            "cssClass": "page-link", 
            "domLevel": 10, 
            "flags": {
                "checkable": false, 
                "clickable": true, 
                "enabled": false, 
                "focusable": true, 
                "focused": false, 
                "scrollable": false
            }, 
            "font-family": "-apple-system, system-ui, \"Segoe UI\", Roboto, \"Helvetica Neue\", Arial, sans-serif, \"Apple Color Emoji\", \"Segoe UI Emoji\", \"Segoe UI Symbol\"", 
            "font-weight": "400", 
            "fontSize": 16, 
            "height": 38, 
            "identifier": "", 
            "is-focused": false, 
            "is-hidden": false, 
            "name": "", 
            "tagName": "a", 
            "text": "3", 
            "type": "", 
            "value": "", 
            "width": 36, 
            "x": 584, 
            "xPercent": 30.406901041666668, 
            "y": 728, 
            "yPercent": 74.82014388489209
        }, 
        "location": {
            "x": 584, 
            "y": 728
        }, 
        "size": {
            "height": 38, 
            "width": 36
        }, 
        "tag_name": "a", 
        "text": "3"
    }, 
    "is_transformed": true, 
    "package": "", 
    "password": false, 
    "resource-id": "", 
    "scrollable": false, 
    "tag_name": "a", 
    "text": "3", 
    "transformed": true, 
    "width": 36, 
    "x": 584, 
    "y": 728
}