{
    "behavior": "", 
    "checkable": false, 
    "class": "div", 
    "clickable": false, 
    "content-desc": "", 
    "elem_shot_file_path": "/Users/bot/test_ai/apps/60f11fb5-ea80-44d0-a9a5-6ae2bbdb1a33/builds/34aaaeb4-52c5-4fe3-b687-5a99e729419d/crawls/20210325235334/tmpZ/div_X390_Y222_W855_H615.png", 
    "enabled": false, 
    "focusable": false, 
    "focused": false, 
    "hash": "fgasWuTnQcHlaVitNMwNfg==\n", 
    "height": 615, 
    "hier_level": 0, 
    "human_hash": "div_X390_Y222_W855_H615", 
    "human_readable": "div_390_222_855_615_div_ffff000000009991fff3fff3fff3fff3fff3fff3fff1fff3fff3ffffffffffff_f8d391840a528325d17df5ed1e2d27f7", 
    "img_hash": "93efe4174096aba23d18c0107e146b66", 
    "index": -1, 
    "internal": {
        "elem_dict": {
            "attributes": {
                "class": "col-md-9"
            }, 
            "background-color": "rgba(0, 0, 0, 0)", 
            "class": "div", 
            "color": "rgb(33, 37, 41)", 
            "cssClass": "col-md-9", 
            "domLevel": 5, 
            "flags": {
                "checkable": false, 
                "clickable": false, 
                "enabled": false, 
                "focusable": false, 
                "focused": false, 
                "scrollable": false
            }, 
            "font-family": "-apple-system, system-ui, \"Segoe UI\", Roboto, \"Helvetica Neue\", Arial, sans-serif, \"Apple Color Emoji\", \"Segoe UI Emoji\", \"Segoe UI Symbol\"", 
            "font-weight": "400", 
            "fontSize": 16, 
            "height": 615, 
            "identifier": "", 
            "is-focused": false, 
            "is-hidden": false, 
            "name": "", 
            "tagName": "div", 
            "text": "Latest Posts\n            \n            \n              \n                \n                  #\n                  Title\n                  Category\n                  Date\n                  \n                \n              \n              \n                \n                  1\n                  Post One\n                  Web Development\n                  May 10 2019\n                  \n                    \n                       Details\n                    \n                  \n                \n                  \n                    2\n                    Post Two\n                    Tech Gadgets\n                    May 11 2019\n                    \n                      \n                         Details\n                      \n                    \n                  \n                    \n                      3\n                      Post Three\n                      Business\n                      May 13 2019\n                      \n                        \n                           Details\n                        \n                      \n                    \n                      \n                        4\n                        Post Four\n                        Web Development\n                        May 15 2019\n                        \n                          \n                             Details\n                          \n                        \n                      \n                        \n                          5\n                          Post Five\n                          Health & Wellness\n                          May 17 2019\n                          \n                            \n                               Details\n                            \n                          \n                        \n                          \n                            6\n                            Post Six\n                            Web Development\n                            May 18 2019\n                            \n                              \n                                 Details", 
            "type": "", 
            "value": "", 
            "width": 855, 
            "x": 390, 
            "xPercent": 20.3125, 
            "y": 222, 
            "yPercent": 21.616358325219085
        }, 
        "location": {
            "x": 390, 
            "y": 222
        }, 
        "size": {
            "height": 615, 
            "width": 855
        }, 
        "tag_name": "div", 
        "text": "Latest Posts\n            \n            \n              \n                \n                  #\n                  Title\n                  Category\n                  Date\n                  \n                \n              \n              \n                \n                  1\n                  Post One\n                  Web Development\n                  May 10 2019\n                  \n                    \n                       Details\n                    \n                  \n                \n                  \n                    2\n                    Post Two\n                    Tech Gadgets\n                    May 11 2019\n                    \n                      \n                         Details\n                      \n                    \n                  \n                    \n                      3\n                      Post Three\n                      Business\n                      May 13 2019\n                      \n                        \n                           Details\n                        \n                      \n                    \n                      \n                        4\n                        Post Four\n                        Web Development\n                        May 15 2019\n                        \n                          \n                             Details\n                          \n                        \n                      \n                        \n                          5\n                          Post Five\n                          Health & Wellness\n                          May 17 2019\n                          \n                            \n                               Details\n                            \n                          \n                        \n                          \n                            6\n                            Post Six\n                            Web Development\n                            May 18 2019\n                            \n                              \n                                 Details"
    }, 
    "is_transformed": true, 
    "package": "", 
    "password": false, 
    "resource-id": "", 
    "scrollable": false, 
    "tag_name": "div", 
    "text": "Latest Posts\n            \n            \n              \n                \n                  #\n                  Title\n                  Category\n                  Date\n                  \n                \n              \n              \n                \n                  1\n                  Post One\n                  Web Development\n                  May 10 2019\n                  \n                    \n                       Details\n                    \n                  \n                \n                  \n                    2\n                    Post Two\n                    Tech Gadgets\n                    May 11 2019\n                    \n                      \n                         Details\n                      \n                    \n                  \n                    \n                      3\n                      Post Three\n                      Business\n                      May 13 2019\n                      \n                        \n                           Details\n                        \n                      \n                    \n                      \n                        4\n                        Post Four\n                        Web Development\n                        May 15 2019\n                        \n                          \n                             Details\n                          \n                        \n                      \n                        \n                          5\n                          Post Five\n                          Health & Wellness\n                          May 17 2019\n                          \n                            \n                               Details\n                            \n                          \n                        \n                          \n                            6\n                            Post Six\n                            Web Development\n                            May 18 2019\n                            \n                              \n                                 Details", 
    "text_hash": "f8d391840a528325d17df5ed1e2d27f7", 
    "transformed": true, 
    "width": 855, 
    "x": 390, 
    "y": 222
}