{
    "behavior": "", 
    "checkable": false, 
    "class": "a", 
    "clickable": true, 
    "content-desc": "", 
    "elem_shot_file_path": "/Users/bot/test_ai/apps/60f11fb5-ea80-44d0-a9a5-6ae2bbdb1a33/builds/34aaaeb4-52c5-4fe3-b687-5a99e729419d/crawls/20210401142334/tmpZ/a_X1353_Y568_W45_H28.png", 
    "enabled": false, 
    "focusable": true, 
    "focused": false, 
    "hash": "P9Ai2Sdeh0Qi22rRXM3mXQ==\n", 
    "height": 28, 
    "hier_level": 0, 
    "human_hash": "a_X1353_Y568_W45_H28", 
    "human_readable": "a_1353_568_45_28_a_ffffffffffff3bf739f73ff73814381138d138d138d108d400d4ffffffffffff_08d500ffd3591dda904e70bb153ba5e8", 
    "img_hash": "f9c2de2ae8ebd21886311648a3ee12a8", 
    "index": -1, 
    "internal": {
        "elem_dict": {
            "attributes": {
                "href": "http://www.google.com"
            }, 
            "background-color": "rgba(0, 0, 0, 0)", 
            "class": "a", 
            "color": "rgb(0, 123, 255)", 
            "domLevel": 11, 
            "flags": {
                "checkable": false, 
                "clickable": true, 
                "enabled": false, 
                "focusable": true, 
                "focused": false, 
                "scrollable": false
            }, 
            "font-family": "-apple-system, system-ui, \"Segoe UI\", Roboto, \"Helvetica Neue\", Arial, sans-serif, \"Apple Color Emoji\", \"Segoe UI Emoji\", \"Segoe UI Symbol\"", 
            "font-weight": "400", 
            "fontSize": 16, 
            "height": 28, 
            "identifier": "", 
            "is-focused": false, 
            "is-hidden": false, 
            "name": "", 
            "tagName": "a", 
            "text": "Link", 
            "type": "", 
            "value": "", 
            "width": 45, 
            "x": 1353, 
            "xPercent": 70.47607421875, 
            "y": 568, 
            "yPercent": 57.31584258324924
        }, 
        "location": {
            "x": 1353, 
            "y": 568
        }, 
        "size": {
            "height": 28, 
            "width": 45
        }, 
        "tag_name": "a", 
        "text": "Link"
    }, 
    "is_transformed": true, 
    "package": "", 
    "password": false, 
    "resource-id": "", 
    "scrollable": false, 
    "tag_name": "a", 
    "text": "Link", 
    "text_hash": "08d500ffd3591dda904e70bb153ba5e8", 
    "transformed": true, 
    "width": 45, 
    "x": 1353, 
    "y": 568
}