{
    "behavior": "", 
    "checkable": false, 
    "class": "button", 
    "clickable": true, 
    "content-desc": "", 
    "elem_shot_file_path": "/Users/bot/test_ai/apps/60f11fb5-ea80-44d0-a9a5-6ae2bbdb1a33/builds/34aaaeb4-52c5-4fe3-b687-5a99e729419d/crawls/20210330161507/tmpZ/button_X208_Y272_W92_H48.png", 
    "enabled": true, 
    "focusable": true, 
    "focused": false, 
    "hash": "vpdj5fk9pbPSLdm8WMfDqQ==\n", 
    "height": 48, 
    "hier_level": 0, 
    "human_hash": "button_X208_Y272_W92_H48", 
    "human_readable": "button_208_272_92_48_button_8001000100010001000118011bf91ff91ff91ff91ff900010001000100018001_b11ddf22124fc20155bdca1c0b516cda", 
    "img_hash": "10aa05995a3fae98fbbd3b07b5c431ff", 
    "index": -1, 
    "internal": {
        "elem_dict": {
            "attributes": {
                "class": "btn btn-primary btn-lg", 
                "type": "button"
            }, 
            "background-color": "rgb(0, 123, 255)", 
            "class": "button", 
            "color": "rgb(255, 255, 255)", 
            "cssClass": "btn btn-primary btn-lg", 
            "domLevel": 8, 
            "flags": {
                "checkable": false, 
                "clickable": true, 
                "enabled": true, 
                "focusable": true, 
                "focused": false, 
                "scrollable": false
            }, 
            "font-family": "-apple-system, system-ui, \"Segoe UI\", Roboto, \"Helvetica Neue\", Arial, sans-serif, \"Apple Color Emoji\", \"Segoe UI Emoji\", \"Segoe UI Symbol\"", 
            "font-weight": "400", 
            "fontSize": 20, 
            "height": 48, 
            "identifier": "", 
            "is-focused": false, 
            "is-hidden": false, 
            "name": "", 
            "tagName": "button", 
            "text": "Button", 
            "type": "button", 
            "value": "", 
            "width": 92, 
            "x": 208, 
            "xPercent": 13.99190829399865, 
            "y": 272, 
            "yPercent": 29.373650107991363
        }, 
        "location": {
            "x": 208, 
            "y": 272
        }, 
        "size": {
            "height": 48, 
            "width": 92
        }, 
        "tag_name": "button", 
        "text": "Button"
    }, 
    "is_transformed": true, 
    "package": "", 
    "password": false, 
    "resource-id": "", 
    "scrollable": false, 
    "tag_name": "button", 
    "text": "Button", 
    "text_hash": "b11ddf22124fc20155bdca1c0b516cda", 
    "transformed": true, 
    "width": 92, 
    "x": 208, 
    "y": 272
}